{
    "parameters": {
        "line": 196,
        "direction": "H",
        "service_time": "09:23:30",
        "comp_percentage": 0.0,
        "node_dist": 200,
        "compulsory_stop_dist": 200,
        "demand_factor": 1,
        "latest_time_factor": 1.5,
        "proposed_time_factor": 0.5,
        "seed": 0,
        "walking_distance": 250,
        "util_value": 1000,
        "fixed_route": false
    },
    "stops": [
        {
            "latitude": 48.1014135,
            "longitude": 11.6463103,
            "is_compulsory": true,
            "order": 0,
            "segment": [
                1
            ],
            "id": 1232834655,
            "name": "Neuperlach Zentrum",
            "earliest_time": "09:23:30",
            "latest_time": "09:23:30"
        },
        {
            "latitude": 48.091358,
            "longitude": 11.6433852,
            "is_compulsory": true,
            "order": 68,
            "segment": [
                1
            ],
            "id": 2700425162,
            "name": "Neuperlach Süd",
            "earliest_time": "09:57:14",
            "latest_time": "09:59:26"
        },
        {
            "latitude": 48.0989385,
            "longitude": 11.6451291,
            "is_compulsory": false,
            "order": 1,
            "segment": [
                1
            ],
            "id": 21551401,
            "name": null,
            "earliest_time": null,
            "latest_time": null
        },
        {
            "latitude": 48.0984931,
            "longitude": 11.6479029,
            "is_compulsory": false,
            "order": 2,
            "segment": [
                1
            ],
            "id": 4129689338,
            "name": null,
            "earliest_time": null,
            "latest_time": null
        },
        {
            "latitude": 48.1007023,
            "longitude": 11.6517977,
            "is_compulsory": false,
            "order": 3,
            "segment": [
                1
            ],
            "id": 206331542,
            "name": null,
            "earliest_time": null,
            "latest_time": null
        },
        {
            "latitude": 48.0962825,
            "longitude": 11.6554361,
            "is_compulsory": false,
            "order": 4,
            "segment": [
                1
            ],
            "id": 15687465,
            "name": null,
            "earliest_time": null,
            "latest_time": null
        },
        {
            "latitude": 48.0977614,
            "longitude": 11.6525199,
            "is_compulsory": false,
            "order": 5,
            "segment": [
                1
            ],
            "id": 15687463,
            "name": null,
            "earliest_time": null,
            "latest_time": null
        },
        {
            "latitude": 48.1003526,
            "longitude": 11.6488738,
            "is_compulsory": false,
            "order": 6,
            "segment": [
                1
            ],
            "id": 298495909,
            "name": null,
            "earliest_time": null,
            "latest_time": null
        },
        {
            "latitude": 48.1035647,
            "longitude": 11.6498432,
            "is_compulsory": false,
            "order": 7,
            "segment": [
                1
            ],
            "id": 15487574,
            "name": null,
            "earliest_time": null,
            "latest_time": null
        },
        {
            "latitude": 48.1036964,
            "longitude": 11.6464556,
            "is_compulsory": false,
            "order": 8,
            "segment": [
                1
            ],
            "id": 413001913,
            "name": null,
            "earliest_time": null,
            "latest_time": null
        },
        {
            "latitude": 48.1063009,
            "longitude": 11.6464527,
            "is_compulsory": false,
            "order": 9,
            "segment": [
                1
            ],
            "id": 24555219,
            "name": null,
            "earliest_time": null,
            "latest_time": null
        },
        {
            "latitude": 48.10918,
            "longitude": 11.6431637,
            "is_compulsory": false,
            "order": 10,
            "segment": [
                1
            ],
            "id": 27186271,
            "name": null,
            "earliest_time": null,
            "latest_time": null
        },
        {
            "latitude": 48.1091719,
            "longitude": 11.6463335,
            "is_compulsory": false,
            "order": 11,
            "segment": [
                1
            ],
            "id": 2041371,
            "name": null,
            "earliest_time": null,
            "latest_time": null
        },
        {
            "latitude": 48.1035901,
            "longitude": 11.6435842,
            "is_compulsory": false,
            "order": 12,
            "segment": [
                1
            ],
            "id": 413013986,
            "name": null,
            "earliest_time": null,
            "latest_time": null
        },
        {
            "latitude": 48.1043536,
            "longitude": 11.6404261,
            "is_compulsory": false,
            "order": 13,
            "segment": [
                1
            ],
            "id": 32947900,
            "name": null,
            "earliest_time": null,
            "latest_time": null
        },
        {
            "latitude": 48.102051,
            "longitude": 11.6345659,
            "is_compulsory": false,
            "order": 14,
            "segment": [
                1
            ],
            "id": 1692411676,
            "name": null,
            "earliest_time": null,
            "latest_time": null
        },
        {
            "latitude": 48.1040799,
            "longitude": 11.633613,
            "is_compulsory": false,
            "order": 15,
            "segment": [
                1
            ],
            "id": 504255702,
            "name": null,
            "earliest_time": null,
            "latest_time": null
        },
        {
            "latitude": 48.1055826,
            "longitude": 11.6489519,
            "is_compulsory": false,
            "order": 16,
            "segment": [
                1
            ],
            "id": 15612632,
            "name": null,
            "earliest_time": null,
            "latest_time": null
        },
        {
            "latitude": 48.1091799,
            "longitude": 11.639306,
            "is_compulsory": false,
            "order": 17,
            "segment": [
                1
            ],
            "id": 27186267,
            "name": null,
            "earliest_time": null,
            "latest_time": null
        },
        {
            "latitude": 48.1068424,
            "longitude": 11.6335867,
            "is_compulsory": false,
            "order": 18,
            "segment": [
                1
            ],
            "id": 27198101,
            "name": null,
            "earliest_time": null,
            "latest_time": null
        },
        {
            "latitude": 48.1068342,
            "longitude": 11.6364595,
            "is_compulsory": false,
            "order": 19,
            "segment": [
                1
            ],
            "id": 15687747,
            "name": null,
            "earliest_time": null,
            "latest_time": null
        },
        {
            "latitude": 48.103256,
            "longitude": 11.6372632,
            "is_compulsory": false,
            "order": 20,
            "segment": [
                1
            ],
            "id": 457091436,
            "name": null,
            "earliest_time": null,
            "latest_time": null
        },
        {
            "latitude": 48.1027944,
            "longitude": 11.6303508,
            "is_compulsory": false,
            "order": 21,
            "segment": [
                1
            ],
            "id": 14785106,
            "name": null,
            "earliest_time": null,
            "latest_time": null
        },
        {
            "latitude": 48.1007556,
            "longitude": 11.6368553,
            "is_compulsory": false,
            "order": 22,
            "segment": [
                1
            ],
            "id": 4184184758,
            "name": null,
            "earliest_time": null,
            "latest_time": null
        },
        {
            "latitude": 48.0994586,
            "longitude": 11.642518,
            "is_compulsory": false,
            "order": 23,
            "segment": [
                1
            ],
            "id": 4192040389,
            "name": null,
            "earliest_time": null,
            "latest_time": null
        },
        {
            "latitude": 48.0988703,
            "longitude": 11.6364934,
            "is_compulsory": false,
            "order": 24,
            "segment": [
                1
            ],
            "id": 4184184768,
            "name": null,
            "earliest_time": null,
            "latest_time": null
        },
        {
            "latitude": 48.099931,
            "longitude": 11.6304036,
            "is_compulsory": false,
            "order": 25,
            "segment": [
                1
            ],
            "id": 1552557688,
            "name": null,
            "earliest_time": null,
            "latest_time": null
        },
        {
            "latitude": 48.0994893,
            "longitude": 11.6334247,
            "is_compulsory": false,
            "order": 26,
            "segment": [
                1
            ],
            "id": 4184184759,
            "name": null,
            "earliest_time": null,
            "latest_time": null
        },
        {
            "latitude": 48.0982276,
            "longitude": 11.6395701,
            "is_compulsory": false,
            "order": 27,
            "segment": [
                1
            ],
            "id": 25877809,
            "name": null,
            "earliest_time": null,
            "latest_time": null
        },
        {
            "latitude": 48.0963881,
            "longitude": 11.6465798,
            "is_compulsory": false,
            "order": 28,
            "segment": [
                1
            ],
            "id": 14658540,
            "name": null,
            "earliest_time": null,
            "latest_time": null
        },
        {
            "latitude": 48.0943613,
            "longitude": 11.6476328,
            "is_compulsory": false,
            "order": 29,
            "segment": [
                1
            ],
            "id": 15688103,
            "name": null,
            "earliest_time": null,
            "latest_time": null
        },
        {
            "latitude": 48.0927083,
            "longitude": 11.6452688,
            "is_compulsory": false,
            "order": 30,
            "segment": [
                1
            ],
            "id": 15488111,
            "name": null,
            "earliest_time": null,
            "latest_time": null
        },
        {
            "latitude": 48.0961003,
            "longitude": 11.64371,
            "is_compulsory": false,
            "order": 31,
            "segment": [
                1
            ],
            "id": 103593950,
            "name": null,
            "earliest_time": null,
            "latest_time": null
        },
        {
            "latitude": 48.0932608,
            "longitude": 11.6422223,
            "is_compulsory": false,
            "order": 32,
            "segment": [
                1
            ],
            "id": 1548827658,
            "name": null,
            "earliest_time": null,
            "latest_time": null
        },
        {
            "latitude": 48.0967812,
            "longitude": 11.634926,
            "is_compulsory": false,
            "order": 33,
            "segment": [
                1
            ],
            "id": 1566687276,
            "name": null,
            "earliest_time": null,
            "latest_time": null
        },
        {
            "latitude": 48.0947624,
            "longitude": 11.6358567,
            "is_compulsory": false,
            "order": 34,
            "segment": [
                1
            ],
            "id": 21675496,
            "name": null,
            "earliest_time": null,
            "latest_time": null
        },
        {
            "latitude": 48.0929438,
            "longitude": 11.6348129,
            "is_compulsory": false,
            "order": 35,
            "segment": [
                1
            ],
            "id": 1544980224,
            "name": null,
            "earliest_time": null,
            "latest_time": null
        },
        {
            "latitude": 48.0977109,
            "longitude": 11.6315261,
            "is_compulsory": false,
            "order": 36,
            "segment": [
                1
            ],
            "id": 1552557684,
            "name": null,
            "earliest_time": null,
            "latest_time": null
        },
        {
            "latitude": 48.0942423,
            "longitude": 11.630963,
            "is_compulsory": false,
            "order": 37,
            "segment": [
                1
            ],
            "id": 21675483,
            "name": null,
            "earliest_time": null,
            "latest_time": null
        },
        {
            "latitude": 48.0970418,
            "longitude": 11.6289057,
            "is_compulsory": false,
            "order": 38,
            "segment": [
                1
            ],
            "id": 171487755,
            "name": null,
            "earliest_time": null,
            "latest_time": null
        },
        {
            "latitude": 48.0960315,
            "longitude": 11.6254949,
            "is_compulsory": false,
            "order": 39,
            "segment": [
                1
            ],
            "id": 4415171268,
            "name": null,
            "earliest_time": null,
            "latest_time": null
        },
        {
            "latitude": 48.0839288,
            "longitude": 11.6273153,
            "is_compulsory": false,
            "order": 40,
            "segment": [
                1
            ],
            "id": 14574966,
            "name": null,
            "earliest_time": null,
            "latest_time": null
        },
        {
            "latitude": 48.0815026,
            "longitude": 11.629139,
            "is_compulsory": false,
            "order": 41,
            "segment": [
                1
            ],
            "id": 14574950,
            "name": null,
            "earliest_time": null,
            "latest_time": null
        },
        {
            "latitude": 48.0817297,
            "longitude": 11.6326133,
            "is_compulsory": false,
            "order": 42,
            "segment": [
                1
            ],
            "id": 571151531,
            "name": null,
            "earliest_time": null,
            "latest_time": null
        },
        {
            "latitude": 48.0850802,
            "longitude": 11.629674,
            "is_compulsory": false,
            "order": 43,
            "segment": [
                1
            ],
            "id": 15913729,
            "name": null,
            "earliest_time": null,
            "latest_time": null
        },
        {
            "latitude": 48.0839902,
            "longitude": 11.6229581,
            "is_compulsory": false,
            "order": 44,
            "segment": [
                1
            ],
            "id": 11598354,
            "name": null,
            "earliest_time": null,
            "latest_time": null
        },
        {
            "latitude": 48.09241,
            "longitude": 11.6248071,
            "is_compulsory": false,
            "order": 45,
            "segment": [
                1
            ],
            "id": 21510741,
            "name": null,
            "earliest_time": null,
            "latest_time": null
        },
        {
            "latitude": 48.0922978,
            "longitude": 11.6280727,
            "is_compulsory": false,
            "order": 46,
            "segment": [
                1
            ],
            "id": 21675477,
            "name": null,
            "earliest_time": null,
            "latest_time": null
        },
        {
            "latitude": 48.0909521,
            "longitude": 11.6305864,
            "is_compulsory": false,
            "order": 47,
            "segment": [
                1
            ],
            "id": 25873668,
            "name": null,
            "earliest_time": null,
            "latest_time": null
        },
        {
            "latitude": 48.0902316,
            "longitude": 11.6278345,
            "is_compulsory": false,
            "order": 48,
            "segment": [
                1
            ],
            "id": 21675476,
            "name": null,
            "earliest_time": null,
            "latest_time": null
        },
        {
            "latitude": 48.0878243,
            "longitude": 11.6279922,
            "is_compulsory": false,
            "order": 49,
            "segment": [
                1
            ],
            "id": 21675464,
            "name": null,
            "earliest_time": null,
            "latest_time": null
        },
        {
            "latitude": 48.0886878,
            "longitude": 11.6347059,
            "is_compulsory": false,
            "order": 50,
            "segment": [
                1
            ],
            "id": 21675444,
            "name": null,
            "earliest_time": null,
            "latest_time": null
        },
        {
            "latitude": 48.0898021,
            "longitude": 11.6350776,
            "is_compulsory": false,
            "order": 51,
            "segment": [
                1
            ],
            "id": 21675453,
            "name": null,
            "earliest_time": null,
            "latest_time": null
        },
        {
            "latitude": 48.0901057,
            "longitude": 11.6405009,
            "is_compulsory": false,
            "order": 52,
            "segment": [
                1
            ],
            "id": 20958552,
            "name": null,
            "earliest_time": null,
            "latest_time": null
        },
        {
            "latitude": 48.0879434,
            "longitude": 11.6389046,
            "is_compulsory": false,
            "order": 53,
            "segment": [
                1
            ],
            "id": 21675429,
            "name": null,
            "earliest_time": null,
            "latest_time": null
        },
        {
            "latitude": 48.0884342,
            "longitude": 11.6358312,
            "is_compulsory": false,
            "order": 54,
            "segment": [
                1
            ],
            "id": 21675417,
            "name": null,
            "earliest_time": null,
            "latest_time": null
        },
        {
            "latitude": 48.0863051,
            "longitude": 11.6347575,
            "is_compulsory": false,
            "order": 55,
            "segment": [
                1
            ],
            "id": 21675422,
            "name": null,
            "earliest_time": null,
            "latest_time": null
        },
        {
            "latitude": 48.0852273,
            "longitude": 11.6394495,
            "is_compulsory": false,
            "order": 56,
            "segment": [
                1
            ],
            "id": 21675404,
            "name": null,
            "earliest_time": null,
            "latest_time": null
        },
        {
            "latitude": 48.087393,
            "longitude": 11.6414775,
            "is_compulsory": false,
            "order": 57,
            "segment": [
                1
            ],
            "id": 21675411,
            "name": null,
            "earliest_time": null,
            "latest_time": null
        },
        {
            "latitude": 48.0870956,
            "longitude": 11.6452412,
            "is_compulsory": false,
            "order": 58,
            "segment": [
                1
            ],
            "id": 2041308,
            "name": null,
            "earliest_time": null,
            "latest_time": null
        },
        {
            "latitude": 48.0818727,
            "longitude": 11.6467445,
            "is_compulsory": false,
            "order": 59,
            "segment": [
                1
            ],
            "id": 15935210,
            "name": null,
            "earliest_time": null,
            "latest_time": null
        },
        {
            "latitude": 48.08352,
            "longitude": 11.6329847,
            "is_compulsory": false,
            "order": 60,
            "segment": [
                1
            ],
            "id": 14574993,
            "name": null,
            "earliest_time": null,
            "latest_time": null
        },
        {
            "latitude": 48.08322,
            "longitude": 11.6366374,
            "is_compulsory": false,
            "order": 61,
            "segment": [
                1
            ],
            "id": 13796730,
            "name": null,
            "earliest_time": null,
            "latest_time": null
        },
        {
            "latitude": 48.0812572,
            "longitude": 11.6500531,
            "is_compulsory": false,
            "order": 62,
            "segment": [
                1
            ],
            "id": 2041294,
            "name": null,
            "earliest_time": null,
            "latest_time": null
        },
        {
            "latitude": 48.0858102,
            "longitude": 11.6498119,
            "is_compulsory": false,
            "order": 63,
            "segment": [
                1
            ],
            "id": 249588687,
            "name": null,
            "earliest_time": null,
            "latest_time": null
        },
        {
            "latitude": 48.0838294,
            "longitude": 11.6484924,
            "is_compulsory": false,
            "order": 64,
            "segment": [
                1
            ],
            "id": 1663079240,
            "name": null,
            "earliest_time": null,
            "latest_time": null
        },
        {
            "latitude": 48.0851124,
            "longitude": 11.6430033,
            "is_compulsory": false,
            "order": 65,
            "segment": [
                1
            ],
            "id": 21675399,
            "name": null,
            "earliest_time": null,
            "latest_time": null
        },
        {
            "latitude": 48.0940843,
            "longitude": 11.651082,
            "is_compulsory": false,
            "order": 66,
            "segment": [
                1
            ],
            "id": 15688106,
            "name": null,
            "earliest_time": null,
            "latest_time": null
        },
        {
            "latitude": 48.0920966,
            "longitude": 11.6522504,
            "is_compulsory": false,
            "order": 67,
            "segment": [
                1
            ],
            "id": 15486479,
            "name": null,
            "earliest_time": null,
            "latest_time": null
        }
    ],
    "route": [
        1232834655,
        413013986,
        298495909,
        21551401,
        25877809,
        4184184758,
        21675496,
        21675483,
        21510741,
        25873668,
        21675417,
        21675422,
        21675404,
        2041308,
        2700425162
    ],
    "requests": [
        {
            "origin": {
                "location": "origin",
                "trip_id": 0,
                "assigned_stop": "Neuperlach Zentrum",
                "lat": 48.10001212403772,
                "lon": 11.64836890984411,
                "building_num": 0
            },
            "destination": {
                "location": "destination",
                "trip_id": 0,
                "assigned_stop": "Perlach Bf.",
                "lat": 48.094625006251846,
                "lon": 11.629875360947398,
                "building_num": 1
            },
            "utility": 1000,
            "is_served": true
        },
        {
            "origin": {
                "location": "origin",
                "trip_id": 1,
                "assigned_stop": "Curd-Jürgens-Straße",
                "lat": 48.085674700000006,
                "lon": 11.642919000000001,
                "building_num": 2
            },
            "destination": {
                "location": "destination",
                "trip_id": 1,
                "assigned_stop": "Neuperlach Süd",
                "lat": 48.08924165000001,
                "lon": 11.644764550000001,
                "building_num": 3
            },
            "utility": 1000,
            "is_served": true
        },
        {
            "origin": {
                "location": "origin",
                "trip_id": 2,
                "assigned_stop": "Ludwig-Linsert-Straße",
                "lat": 48.0859676658514,
                "lon": 11.63460440148319,
                "building_num": 4
            },
            "destination": {
                "location": "destination",
                "trip_id": 2,
                "assigned_stop": "Ludwig-Erhard-Allee",
                "lat": 48.08703514300411,
                "lon": 11.641141191714707,
                "building_num": 5
            },
            "utility": 1000,
            "is_served": true
        },
        {
            "origin": {
                "location": "origin",
                "trip_id": 3,
                "assigned_stop": "Neuperlach Zentrum",
                "lat": 48.10107489999999,
                "lon": 11.646810649999999,
                "building_num": 6
            },
            "destination": {
                "location": "destination",
                "trip_id": 3,
                "assigned_stop": "Weidener Straße",
                "lat": 48.093571823833585,
                "lon": 11.626670530456503,
                "building_num": 7
            },
            "utility": 1000,
            "is_served": true
        },
        {
            "origin": {
                "location": "origin",
                "trip_id": 4,
                "assigned_stop": "Neuperlach Zentrum",
                "lat": 48.101723406163224,
                "lon": 11.64927397530927,
                "building_num": 8
            },
            "destination": {
                "location": "destination",
                "trip_id": 4,
                "assigned_stop": "Wolframstraße",
                "lat": 48.09511376500166,
                "lon": 11.637008227013876,
                "building_num": 9
            },
            "utility": 1000,
            "is_served": true
        },
        {
            "origin": {
                "location": "origin",
                "trip_id": 5,
                "assigned_stop": "Weidener Straße",
                "lat": 48.09341215,
                "lon": 11.63009625,
                "building_num": 10
            },
            "destination": {
                "location": "destination",
                "trip_id": 5,
                "assigned_stop": "Neuperlach Süd",
                "lat": 48.08913009374481,
                "lon": 11.644888500360345,
                "building_num": 11
            },
            "utility": 1000,
            "is_served": true
        },
        {
            "origin": {
                "location": "origin",
                "trip_id": 6,
                "assigned_stop": "Neuperlach Zentrum",
                "lat": 48.10153970751716,
                "lon": 11.650376852730036,
                "building_num": 12
            },
            "destination": {
                "location": "destination",
                "trip_id": 6,
                "assigned_stop": "Jakob-Kaiser-Straße",
                "lat": 48.104965124877474,
                "lon": 11.641239012155381,
                "building_num": 13
            },
            "utility": 1000,
            "is_served": true
        },
        {
            "origin": {
                "location": "origin",
                "trip_id": 7,
                "assigned_stop": "Neuperlach Zentrum",
                "lat": 48.10187581870805,
                "lon": 11.643503272798954,
                "building_num": 14
            },
            "destination": {
                "location": "destination",
                "trip_id": 7,
                "assigned_stop": "Wolframstraße",
                "lat": 48.0964652637103,
                "lon": 11.638929261343831,
                "building_num": 15
            },
            "utility": 1000,
            "is_served": true
        },
        {
            "origin": {
                "location": "origin",
                "trip_id": 8,
                "assigned_stop": "Holzwiesenstraße",
                "lat": 48.10138596536984,
                "lon": 11.638023647162612,
                "building_num": 16
            },
            "destination": {
                "location": "destination",
                "trip_id": 8,
                "assigned_stop": "Neuperlach Süd",
                "lat": 48.08833099346861,
                "lon": 11.644316479721065,
                "building_num": 17
            },
            "utility": 1000,
            "is_served": true
        },
        {
            "origin": {
                "location": "origin",
                "trip_id": 9,
                "assigned_stop": "Neuperlach Zentrum",
                "lat": 48.10129805866731,
                "lon": 11.64584605543322,
                "building_num": 18
            },
            "destination": {
                "location": "destination",
                "trip_id": 9,
                "assigned_stop": "Nailastraße",
                "lat": 48.08585565,
                "lon": 11.629774049999998,
                "building_num": 19
            },
            "utility": 1000,
            "is_served": false
        },
        {
            "origin": {
                "location": "origin",
                "trip_id": 10,
                "assigned_stop": "Perlach Bf.",
                "lat": 48.09514243529047,
                "lon": 11.628511747375942,
                "building_num": 20
            },
            "destination": {
                "location": "destination",
                "trip_id": 10,
                "assigned_stop": "Nailastraße",
                "lat": 48.089481750000004,
                "lon": 11.631998000000001,
                "building_num": 21
            },
            "utility": 1000,
            "is_served": true
        },
        {
            "origin": {
                "location": "origin",
                "trip_id": 11,
                "assigned_stop": "Neuperlach Zentrum",
                "lat": 48.098944930225116,
                "lon": 11.643284486475592,
                "building_num": 22
            },
            "destination": {
                "location": "destination",
                "trip_id": 11,
                "assigned_stop": "Weidener Straße",
                "lat": 48.0935023701496,
                "lon": 11.625127630823238,
                "building_num": 23
            },
            "utility": 1000,
            "is_served": true
        },
        {
            "origin": {
                "location": "origin",
                "trip_id": 12,
                "assigned_stop": "Nailastraße",
                "lat": 48.08926005000001,
                "lon": 11.634410850000002,
                "building_num": 24
            },
            "destination": {
                "location": "destination",
                "trip_id": 12,
                "assigned_stop": "Neuperlach Süd",
                "lat": 48.08913909845644,
                "lon": 11.644912504260708,
                "building_num": 25
            },
            "utility": 1000,
            "is_served": true
        },
        {
            "origin": {
                "location": "origin",
                "trip_id": 13,
                "assigned_stop": "Ludwig-Erhard-Allee",
                "lat": 48.08597641396646,
                "lon": 11.640162356304161,
                "building_num": 26
            },
            "destination": {
                "location": "destination",
                "trip_id": 13,
                "assigned_stop": "Neuperlach Süd",
                "lat": 48.089167350000004,
                "lon": 11.64484695,
                "building_num": 27
            },
            "utility": 1000,
            "is_served": true
        },
        {
            "origin": {
                "location": "origin",
                "trip_id": 14,
                "assigned_stop": "Neuperlach Zentrum",
                "lat": 48.10142576831468,
                "lon": 11.647907148166716,
                "building_num": 28
            },
            "destination": {
                "location": "destination",
                "trip_id": 14,
                "assigned_stop": "Holzwiesenstraße",
                "lat": 48.10228870363619,
                "lon": 11.637533411365602,
                "building_num": 29
            },
            "utility": 1000,
            "is_served": true
        }
    ],
    "kpi": {
        "km_travel_distance": 8.5,
        "kWh_consumption_1.5_kWh_x_km": 12.74,
        "minutes_travel_time": 31.68,
        "num_total_request": 15,
        "num_served_requests": 14,
        "meters_total_walking_distance": 3721.85,
        "arrival_times_at_compulsory_stops": [
            "09:23:30",
            "09:57:14"
        ]
    }
}